contsys/__init__.py
contsys/function.py
contsys-1.3.1.dist-info/licenses/LICENSE
contsys-1.3.1.dist-info/METADATA
contsys-1.3.1.dist-info/WHEEL
contsys-1.3.1.dist-info/top_level.txt
contsys-1.3.1.dist-info/RECORD
