Metadata-Version: 2.4
Name: contsys
Version: 1.3.1
Summary: Python library simplifying system script management with handy functions like clearing the console, setting the window title, and detecting the operating system (Windows, Linux, macOS).
Author-email: G-Azon <G-Azon782345@protonmail.com>
License: MIT
Classifier: Programming Language :: Python :: 3
Classifier: License :: OSI Approved :: MIT License
Classifier: Operating System :: OS Independent
Requires-Python: >=3.11
License-File: LICENSE
Dynamic: license-file
